VIVOHarvester-0.2.2.data/scripts/vivotool
test/__init__.py
test/test2.py
test/test_file_utils.py
test/test_harvester.py
test/test_model_publication.py
test/test_model_user.py
test/test_publication.py
test/test_relation.py
test/test_relationship_to_rdf.py
test/test_user.py
test/test_utils.py
test/test_vivo.py
test/testconf.py
test/testfiles.py
test/testingest.py
test/testingest2.py
test/testother.py
vivotool/__init__.py
vivotool/command_line.py
vivotool/test.py
vivotool/harvester/__init__.py
vivotool/harvester/elements.py
vivotool/harvester/elementsharvester.py
vivotool/tests/__init__.py
vivotool/tests/test_file_utils.py
vivotool/tests/test_harvester.py
vivotool/tests/test_model_publication.py
vivotool/tests/test_model_relation.py
vivotool/tests/test_model_user.py
vivotool/tests/test_publication.py
vivotool/tests/test_relation.py
vivotool/tests/test_user.py
vivotool/tests/test_utils.py
vivotool/tests/test_vivo.py
vivotool/utils/__init__.py
vivotool/utils/db.py
vivotool/utils/file_utils.py
vivotool/utils/misc.py
vivotool/utils/photo.py
vivotool/utils/publicationxmltordf.py
vivotool/utils/relationxmltordf.py
vivotool/utils/transform.py
vivotool/utils/userxmltordf.py
vivotool/utils/models/__init__.py
vivotool/utils/models/publication_model.py
vivotool/utils/models/relationship_models.py
vivotool/utils/models/user_model.py
vivotool/vivo/__init__.py
vivotool/vivo/vivo.py
vivotool/vivo/vivo_utils.py
VIVOHarvester-0.2.2.dist-info/LICENSE
VIVOHarvester-0.2.2.dist-info/METADATA
VIVOHarvester-0.2.2.dist-info/WHEEL
VIVOHarvester-0.2.2.dist-info/top_level.txt
VIVOHarvester-0.2.2.dist-info/RECORD
