Metadata-Version: 2.1
Name: VIVOHarvester
Version: 0.2.2
Summary: VIVO harvester
Home-page: https://github.com/VTUL/VIVOHarvester
Author: Yinlin Chen, Tingting Jiang, Lee Hunter
Author-email: ylchen@vt.edu, virjtt03@vt.edu, whunter@vt.edu
License: MIT
Platform: UNKNOWN
Classifier: Programming Language :: Python :: 2.7
Classifier: License :: OSI Approved :: MIT License
Classifier: Operating System :: OS Independent
Requires-Dist: nose
Requires-Dist: rdflib
Requires-Dist: xmltodict
Requires-Dist: pyyaml
Requires-Dist: lxml
Requires-Dist: requests
Requires-Dist: cryptography
Requires-Dist: pytz
Requires-Dist: pymysql
